SimpleMorphoMath/MathplotlibTools.py
SimpleMorphoMath/PrettyPrinting.py
SimpleMorphoMath/SimpleMorphoMath1D.py
SimpleMorphoMath/SimpleMorphoMath2D.py
SimpleMorphoMath/__init__.py
SimpleMorphoMath-1.0.0.dist-info/DESCRIPTION.rst
SimpleMorphoMath-1.0.0.dist-info/METADATA
SimpleMorphoMath-1.0.0.dist-info/RECORD
SimpleMorphoMath-1.0.0.dist-info/WHEEL
SimpleMorphoMath-1.0.0.dist-info/metadata.json
SimpleMorphoMath-1.0.0.dist-info/top_level.txt
