Metadata-Version: 2.0
Name: SimpleMorphoMath
Version: 1.0.0
Summary: A simple mathematical morphology library
Home-page: https://github.com/FabriceSalvaire/SimpleMorphoMath
Author: Fabrice Salvaire
Author-email: fabrice.salvaire@orange.fr
License: GPLv3
Keywords: mathematical morphology
Platform: any
Classifier: Topic :: Scientific/Engineering
Classifier: Intended Audience :: Education
Classifier: Development Status :: 5 - Production/Stable
Classifier: License :: OSI Approved :: GNU General Public License v3 (GPLv3)
Classifier: Operating System :: OS Independent
Classifier: Programming Language :: Python :: 3.0
Requires-Dist: numpy
